md_harmonize-1.0.4.data/platlib/_custom_build.py
md_harmonize-1.0.4.data/platlib/md_harmonize/BASS.c
md_harmonize-1.0.4.data/platlib/md_harmonize/BASS.cpython-310-x86_64-linux-gnu.so
md_harmonize-1.0.4.data/platlib/md_harmonize/BASS.pyx
md_harmonize-1.0.4.data/platlib/md_harmonize/KEGG_database_scraper.py
md_harmonize-1.0.4.data/platlib/md_harmonize/KEGG_parser.py
md_harmonize-1.0.4.data/platlib/md_harmonize/MetaCyc_parser.py
md_harmonize-1.0.4.data/platlib/md_harmonize/__init__.py
md_harmonize-1.0.4.data/platlib/md_harmonize/__main__.py
md_harmonize-1.0.4.data/platlib/md_harmonize/aromatics.py
md_harmonize-1.0.4.data/platlib/md_harmonize/compound.py
md_harmonize-1.0.4.data/platlib/md_harmonize/harmonization.py
md_harmonize-1.0.4.data/platlib/md_harmonize/openbabel_utils.py
md_harmonize-1.0.4.data/platlib/md_harmonize/reaction.py
md_harmonize-1.0.4.data/platlib/md_harmonize/supplement.py
md_harmonize-1.0.4.data/platlib/md_harmonize/tools.py
md_harmonize-1.0.4.data/platlib/md_harmonize/uncythonized_BASS.py
md_harmonize-1.0.4.data/platlib/md_harmonize/supplements/supplementary_data.json
md_harmonize-1.0.4.dist-info/LICENSE
md_harmonize-1.0.4.dist-info/METADATA
md_harmonize-1.0.4.dist-info/WHEEL
md_harmonize-1.0.4.dist-info/entry_points.txt
md_harmonize-1.0.4.dist-info/top_level.txt
md_harmonize-1.0.4.dist-info/RECORD
