Metadata-Version: 2.1
Name: md-harmonize
Version: 1.0.4
Summary: Harmonize compounds and reactions across public metabolic databases.
License: A modified Clear BSD License
Project-URL: Homepage, https://github.com/MoseleyBioinformaticsLab/md_harmonize
Project-URL: Documentation, https://moseleybioinformaticslab.github.io/md_harmonize/
Project-URL: GitHub, https://github.com/MoseleyBioinformaticsLab/md_harmonize
Keywords: metabolic database,harmonization
Classifier: Environment :: Console
Classifier: Intended Audience :: Developers
Classifier: Intended Audience :: Science/Research
Classifier: License :: OSI Approved :: BSD License
Classifier: Operating System :: OS Independent
Classifier: Programming Language :: Python :: 3.7
Classifier: Programming Language :: Python :: 3.8
Classifier: Programming Language :: Python :: 3.9
Classifier: Programming Language :: Python :: 3.10
Classifier: Topic :: Scientific/Engineering :: Bio-Informatics
Classifier: Topic :: Software Development :: Libraries :: Python Modules
Requires-Python: >=3.7
License-File: LICENSE
Requires-Dist: sphinx
Requires-Dist: sphinxcontrib-napoleon
Requires-Dist: sphinx-rtd-theme
Requires-Dist: docopt
Requires-Dist: jsonpickle
Requires-Dist: numpy
Requires-Dist: epam.indigo
Requires-Dist: ctfile
Requires-Dist: Cython
Requires-Dist: Pebble
